hello_mnv/__init__.py
hello_mnv/__main__.py
hello_mnv-0.0.2.dist-info/LICENSE.txt
hello_mnv-0.0.2.dist-info/METADATA
hello_mnv-0.0.2.dist-info/WHEEL
hello_mnv-0.0.2.dist-info/top_level.txt
hello_mnv-0.0.2.dist-info/RECORD
