Metadata-Version: 2.1
Name: hello-mnv
Version: 0.0.2
Summary: A small package which prints hello on the screen :)
Home-page: https://github.com/pypa/sampleproject
Author: Manav Upadhyay
Author-email: manavupadhyay5@gmail.com
License: UNKNOWN
Platform: UNKNOWN
Classifier: Programming Language :: Python :: 3
Classifier: License :: OSI Approved :: MIT License
Classifier: Operating System :: OS Independent
Requires-Python: >=3.6
